disjoint_generation/__init__.py
disjoint_generation/disjoint_model.py
disjoint_generation/utils/__init__.py
disjoint_generation/utils/dataset_manager.py
disjoint_generation/utils/generative_model_adapters.py
disjoint_generation/utils/joining_strategies.py
disjoint_generation/utils/joining_validator.py
disjoint_generation/utils/plots.py
disjoint_generation/utils/subprocess/__init__.py
disjoint_generation/utils/subprocess/synthpop_subprocess.R
disjoint_generation-1.0.dist-info/METADATA
disjoint_generation-1.0.dist-info/WHEEL
disjoint_generation-1.0.dist-info/licenses/LICENSE
disjoint_generation-1.0.dist-info/RECORD
