Metadata-Version: 2.4
Name: disjoint_generation
Version: 1.0
Summary: Exploring the Effects of Disjoint Generation of Synthetic Tabular Data.
Author: Anton D. Lautrup, Muhammad Rajabinasab
License-File: LICENSE
Classifier: License :: OSI Approved :: MIT License
Classifier: Operating System :: OS Independent
Classifier: Programming Language :: Python :: 3
Requires-Python: >=3.10
Requires-Dist: datasynthesizer~=0.1.13
Requires-Dist: numpy
Requires-Dist: pandas
Requires-Dist: pyod>=2.0
Requires-Dist: pytest-doctest-ellipsis-markers
Requires-Dist: scikit-learn~=1.5
Requires-Dist: scipy~=1.12
Requires-Dist: synthcity>=0.2.11
Requires-Dist: syntheval>=1.6.0
